{"nodes": [{"id": "inventory_background_panel", "label": "Inventory Background Panel", "file_type": "image", "source_file": "Assets/UI/GameMenu/InventoryPage/Background/inventory.png", "source_location": null, "source_url": null, "captured_at": null, "author": null, "contributor": null}, {"id": "inventory_panel_dark_theme", "label": "Dark/Worn Metal Visual Theme", "file_type": "image", "source_file": "Assets/UI/GameMenu/InventoryPage/Background/inventory.png", "source_location": null, "source_url": null, "captured_at": null, "author": null, "contributor": null}, {"id": "inventory_panel_border", "label": "Inventory Panel Border Frame", "file_type": "image", "source_file": "Assets/UI/GameMenu/InventoryPage/Background/inventory.png", "source_location": null, "source_url": null, "captured_at": null, "author": null, "contributor": null}, {"id": "inventory_panel_hinge", "label": "Left-Side Hinge/Clasp Detail", "file_type": "image", "source_file": "Assets/UI/GameMenu/InventoryPage/Background/inventory.png", "source_location": null, "source_url": null, "captured_at": null, "author": null, "contributor": null}, {"id": "inventory_panel_corner_rivets", "label": "Corner Rivet/Bolt Details", "file_type": "image", "source_file": "Assets/UI/GameMenu/InventoryPage/Background/inventory.png", "source_location": null, "source_url": null, "captured_at": null, "author": null, "contributor": null}, {"id": "inventory_page", "label": "InventoryPage UI Screen", "file_type": "image", "source_file": "Assets/UI/GameMenu/InventoryPage/Background/inventory.png", "source_location": null, "source_url": null, "captured_at": null, "author": null, "contributor": null}], "edges": [], "hyperedges": []}